mixgarden/__init__.py
mixgarden/client.py
mixgarden-0.1.3.dist-info/METADATA
mixgarden-0.1.3.dist-info/WHEEL
mixgarden-0.1.3.dist-info/RECORD
