Metadata-Version: 2.4
Name: mixgarden
Version: 0.1.3
Summary: Python SDK for the Mixgarden API
Author-email: Mixgarden <admin@mixgarden.ai>
License: MIT
Keywords: ai,llm,mixgarden,sdk
Requires-Python: >=3.9
Requires-Dist: httpx>=0.27
